masscodeDriver/__init__.py
masscodeDriver/apploader.py
masscodeDriver/datacls.py
masscodeDriver/model.py
masscodeDriver/utils.py
masscode_driver-1.0.3.dist-info/LICENSE
masscode_driver-1.0.3.dist-info/METADATA
masscode_driver-1.0.3.dist-info/WHEEL
masscode_driver-1.0.3.dist-info/top_level.txt
masscode_driver-1.0.3.dist-info/RECORD
