Metadata-Version: 2.1
Name: masscode-driver
Version: 1.0.3
Summary: Driver for MassCode
Home-page: https://github.com/ZackaryW/masscode-driver
Author: ZackaryW
License: MIT
Classifier: Programming Language :: Python :: 3
Classifier: License :: OSI Approved :: MIT License
Classifier: Intended Audience :: Developers
Requires-Python: >=3.8
License-File: LICENSE
Requires-Dist: thefuzz
